{
  "db_name": "PostgreSQL",
  "query": "\n            UPDATE etherscan_verification_requests\n            SET\n                attempts = attempts + 1,\n                status = $2,\n                updated_at = NOW(),\n                error = $3\n            WHERE\n                contract_verification_request_id = $1\n            ",
  "describe": {
    "columns": [],
    "parameters": {
      "Left": [
        "Int8",
        "Varchar",
        "Text"
      ]
    },
    "nullable": []
  },
  "hash": "fdb22f30f346ec0937fb774ad30c245087b86a773aed978bc59c6fe48e1fc271"
}
