{
  "db_name": "PostgreSQL",
  "query": "\n            UPDATE tokens\n            SET\n                token_list_name = $2,\n                token_list_symbol = $3,\n                token_list_decimals = $4,\n                well_known = TRUE,\n                updated_at = NOW()\n            WHERE\n                l1_address = $1\n            ",
  "describe": {
    "columns": [],
    "parameters": {
      "Left": [
        "Bytea",
        "Varchar",
        "Varchar",
        "Int4"
      ]
    },
    "nullable": []
  },
  "hash": "08ff0c774a501a12486964f912f5f5f6a43476b1352116a643c680751dd4800f"
}
