{
  "db_name": "PostgreSQL",
  "query": "\n                UPDATE prover_jobs\n                SET\n                    status = 'queued',\n                    updated_at = NOW(),\n                    processing_started_at = NOW()\n                WHERE\n                    (\n                        status = 'in_progress'\n                        AND processing_started_at <= NOW() - $1::INTERVAL\n                        AND attempts < $2\n                    )\n                    OR (\n                        status = 'in_gpu_proof'\n                        AND processing_started_at <= NOW() - $1::INTERVAL\n                        AND attempts < $2\n                    )\n                    OR (\n                        status = 'failed'\n                        AND attempts < $2\n                    )\n                RETURNING\n                    id,\n                    status,\n                    attempts\n                ",
  "describe": {
    "columns": [
      {
        "ordinal": 0,
        "name": "id",
        "type_info": "Int8"
      },
      {
        "ordinal": 1,
        "name": "status",
        "type_info": "Text"
      },
      {
        "ordinal": 2,
        "name": "attempts",
        "type_info": "Int4"
      }
    ],
    "parameters": {
      "Left": [
        "Interval",
        "Int4"
      ]
    },
    "nullable": [
      false,
      false,
      false
    ]
  },
  "hash": "f303c53843a58fac4fcdedbfe2b2b33ad609b7df8e55a0cf214ea1ec6421e57a"
}
